quick_scheme/__init__.py
quick_scheme/base_node.py
quick_scheme/exceptions.py
quick_scheme/field.py
quick_scheme/field_test.py
quick_scheme/proxy_access_test.py
quick_scheme/qs_yaml.py
quick_scheme/utils.py
quick_scheme/nodes/__init__.py
quick_scheme/nodes/key_based_list.py
quick_scheme/nodes/key_based_list_test.py
quick_scheme/nodes/list_of_nodes.py
quick_scheme/nodes/list_of_references.py
quick_scheme/nodes/scheme_node.py
quick_scheme/nodes/scheme_node_test.py
quick_scheme/validators/__init__.py
quick_scheme/validators/combinations.py
quick_scheme/validators/combinations_test.py
quick_scheme/validators/common.py
quick_scheme/validators/number_validators.py
quick_scheme/validators/number_validators_test.py
quick_scheme/validators/string_validators.py
quick_scheme/validators/string_validators_test.py
QuickScheme-0.2.0.dist-info/LICENSE
QuickScheme-0.2.0.dist-info/METADATA
QuickScheme-0.2.0.dist-info/WHEEL
QuickScheme-0.2.0.dist-info/top_level.txt
QuickScheme-0.2.0.dist-info/RECORD
