Metadata-Version: 2.1
Name: QuickScheme
Version: 0.2.0
Summary: Quick Way To Define Data Schema and Mapping Data To Objects
Home-page: https://mlasevich.github.io/QuickScheme/
Author: Michael Lasevich
Author-email: mlasevich+quick@gmail.com
License: Apache 2.0
Platform: UNKNOWN
Classifier: Programming Language :: Python :: 3
Classifier: Programming Language :: Python :: 2.7
Classifier: License :: OSI Approved :: Apache Software License
Classifier: Operating System :: OS Independent
Requires-Dist: PyYaml
Requires-Dist: future
